Metadata-Version: 2.1
Name: bucketit
Version: 0.5
Summary: BucketIt is a CLI tool for uploading files to S3 bucket.
Home-page: https://github.com/sazonovanton/BucketIt
Author: Anton Sazonov
License: MIT
Project-URL: Source, https://github.com/sazonovanton/BucketIt
Keywords: BucketIt CLI Tool
Platform: UNKNOWN
Classifier: Development Status :: 3 - Alpha
Classifier: Intended Audience :: Developers
Classifier: Programming Language :: Python
Classifier: Programming Language :: Python :: 3
Classifier: Programming Language :: Python :: 3
Classifier: Programming Language :: Python :: 3.7
Classifier: Programming Language :: Python :: 3.8
Classifier: Programming Language :: Python :: 3.9
Classifier: Programming Language :: Python :: 3.10
Classifier: Programming Language :: Python :: 3.11
Classifier: License :: OSI Approved :: GNU General Public License v3 (GPLv3)
